{"nodes": [{"id": "data_model_doc", "label": "CourseBridge Data Model Draft", "file_type": "document", "source_file": "docs/data-model.md", "source_location": null, "source_url": null, "captured_at": null, "author": null, "contributor": null}, {"id": "status_course_created", "label": "Status: course_created", "file_type": "document", "source_file": "docs/data-model.md", "source_location": null, "source_url": null, "captured_at": null, "author": null, "contributor": null}, {"id": "status_assigned_to_ta", "label": "Status: assigned_to_ta", "file_type": "document", "source_file": "docs/data-model.md", "source_location": null, "source_url": null, "captured_at": null, "author": null, "contributor": null}, {"id": "status_ta_review_in_progress", "label": "Status: ta_review_in_progress", "file_type": "document", "source_file": "docs/data-model.md", "source_location": null, "source_url": null, "captured_at": null, "author": null, "contributor": null}, {"id": "status_submitted_to_admin", "label": "Status: submitted_to_admin", "file_type": "document", "source_file": "docs/data-model.md", "source_location": null, "source_url": null, "captured_at": null, "author": null, "contributor": null}, {"id": "status_admin_changes_requested", "label": "Status: admin_changes_requested", "file_type": "document", "source_file": "docs/data-model.md", "source_location": null, "source_url": null, "captured_at": null, "author": null, "contributor": null}, {"id": "status_ready_for_instructor", "label": "Status: ready_for_instructor", "file_type": "document", "source_file": "docs/data-model.md", "source_location": null, "source_url": null, "captured_at": null, "author": null, "contributor": null}, {"id": "status_sent_to_instructor", "label": "Status: sent_to_instructor", "file_type": "document", "source_file": "docs/data-model.md", "source_location": null, "source_url": null, "captured_at": null, "author": null, "contributor": null}, {"id": "status_instructor_questions", "label": "Status: instructor_questions", "file_type": "document", "source_file": "docs/data-model.md", "source_location": null, "source_url": null, "captured_at": null, "author": null, "contributor": null}, {"id": "status_instructor_approved", "label": "Status: instructor_approved", "file_type": "document", "source_file": "docs/data-model.md", "source_location": null, "source_url": null, "captured_at": null, "author": null, "contributor": null}, {"id": "status_final_approved", "label": "Status: final_approved", "file_type": "document", "source_file": "docs/data-model.md", "source_location": null, "source_url": null, "captured_at": null, "author": null, "contributor": null}, {"id": "table_profiles", "label": "DB Table: profiles", "file_type": "document", "source_file": "docs/data-model.md", "source_location": null, "source_url": null, "captured_at": null, "author": null, "contributor": null}, {"id": "table_courses", "label": "DB Table: courses", "file_type": "document", "source_file": "docs/data-model.md", "source_location": null, "source_url": null, "captured_at": null, "author": null, "contributor": null}, {"id": "table_course_assignments", "label": "DB Table: course_assignments", "file_type": "document", "source_file": "docs/data-model.md", "source_location": null, "source_url": null, "captured_at": null, "author": null, "contributor": null}, {"id": "table_course_status_events", "label": "DB Table: course_status_events", "file_type": "document", "source_file": "docs/data-model.md", "source_location": null, "source_url": null, "captured_at": null, "author": null, "contributor": null}, {"id": "table_review_sections", "label": "DB Table: review_sections", "file_type": "document", "source_file": "docs/data-model.md", "source_location": null, "source_url": null, "captured_at": null, "author": null, "contributor": null}, {"id": "table_review_responses", "label": "DB Table: review_responses", "file_type": "document", "source_file": "docs/data-model.md", "source_location": null, "source_url": null, "captured_at": null, "author": null, "contributor": null}, {"id": "table_course_comments", "label": "DB Table: course_comments", "file_type": "document", "source_file": "docs/data-model.md", "source_location": null, "source_url": null, "captured_at": null, "author": null, "contributor": null}, {"id": "table_review_invites", "label": "DB Table: review_invites", "file_type": "document", "source_file": "docs/data-model.md", "source_location": null, "source_url": null, "captured_at": null, "author": null, "contributor": null}, {"id": "auth_users_supabase", "label": "auth.users (Supabase owned)", "file_type": "document", "source_file": "docs/data-model.md", "source_location": null, "source_url": null, "captured_at": null, "author": null, "contributor": null}, {"id": "review_section_course_metadata", "label": "Review Section: course_metadata", "file_type": "document", "source_file": "docs/data-model.md", "source_location": null, "source_url": null, "captured_at": null, "author": null, "contributor": null}, {"id": "review_section_review_matrix", "label": "Review Section: review_matrix", "file_type": "document", "source_file": "docs/data-model.md", "source_location": null, "source_url": null, "captured_at": null, "author": null, "contributor": null}, {"id": "review_section_syllabus_review", "label": "Review Section: syllabus_review", "file_type": "document", "source_file": "docs/data-model.md", "source_location": null, "source_url": null, "captured_at": null, "author": null, "contributor": null}, {"id": "review_section_gradebook_review", "label": "Review Section: gradebook_review", "file_type": "document", "source_file": "docs/data-model.md", "source_location": null, "source_url": null, "captured_at": null, "author": null, "contributor": null}, {"id": "review_section_general_notes", "label": "Review Section: general_notes", "file_type": "document", "source_file": "docs/data-model.md", "source_location": null, "source_url": null, "captured_at": null, "author": null, "contributor": null}], "edges": [{"source": "data_model_doc", "target": "workflow_transitions_doc", "relation": "conceptually_related_to", "confidence": "EXTRACTED", "confidence_score": 1.0, "source_file": "docs/data-model.md", "source_location": null, "weight": 1.0}, {"source": "data_model_doc", "target": "pkg_workflow_readme", "relation": "references", "confidence": "EXTRACTED", "confidence_score": 1.0, "source_file": "docs/data-model.md", "source_location": null, "weight": 1.0}, {"source": "data_model_doc", "target": "table_profiles", "relation": "references", "confidence": "EXTRACTED", "confidence_score": 1.0, "source_file": "docs/data-model.md", "source_location": null, "weight": 1.0}, {"source": "data_model_doc", "target": "table_courses", "relation": "references", "confidence": "EXTRACTED", "confidence_score": 1.0, "source_file": "docs/data-model.md", "source_location": null, "weight": 1.0}, {"source": "data_model_doc", "target": "table_course_assignments", "relation": "references", "confidence": "EXTRACTED", "confidence_score": 1.0, "source_file": "docs/data-model.md", "source_location": null, "weight": 1.0}, {"source": "data_model_doc", "target": "table_course_status_events", "relation": "references", "confidence": "EXTRACTED", "confidence_score": 1.0, "source_file": "docs/data-model.md", "source_location": null, "weight": 1.0}, {"source": "data_model_doc", "target": "table_review_sections", "relation": "references", "confidence": "EXTRACTED", "confidence_score": 1.0, "source_file": "docs/data-model.md", "source_location": null, "weight": 1.0}, {"source": "data_model_doc", "target": "table_review_responses", "relation": "references", "confidence": "EXTRACTED", "confidence_score": 1.0, "source_file": "docs/data-model.md", "source_location": null, "weight": 1.0}, {"source": "data_model_doc", "target": "table_course_comments", "relation": "references", "confidence": "EXTRACTED", "confidence_score": 1.0, "source_file": "docs/data-model.md", "source_location": null, "weight": 1.0}, {"source": "data_model_doc", "target": "table_review_invites", "relation": "references", "confidence": "EXTRACTED", "confidence_score": 1.0, "source_file": "docs/data-model.md", "source_location": null, "weight": 1.0}, {"source": "table_profiles", "target": "auth_users_supabase", "relation": "references", "confidence": "EXTRACTED", "confidence_score": 1.0, "source_file": "docs/data-model.md", "source_location": null, "weight": 1.0}, {"source": "table_courses", "target": "table_course_assignments", "relation": "shares_data_with", "confidence": "EXTRACTED", "confidence_score": 1.0, "source_file": "docs/data-model.md", "source_location": null, "weight": 1.0}, {"source": "table_courses", "target": "table_review_responses", "relation": "shares_data_with", "confidence": "EXTRACTED", "confidence_score": 1.0, "source_file": "docs/data-model.md", "source_location": null, "weight": 1.0}, {"source": "table_courses", "target": "table_course_comments", "relation": "shares_data_with", "confidence": "EXTRACTED", "confidence_score": 1.0, "source_file": "docs/data-model.md", "source_location": null, "weight": 1.0}, {"source": "table_courses", "target": "table_course_status_events", "relation": "shares_data_with", "confidence": "EXTRACTED", "confidence_score": 1.0, "source_file": "docs/data-model.md", "source_location": null, "weight": 1.0}, {"source": "table_courses", "target": "table_review_invites", "relation": "shares_data_with", "confidence": "EXTRACTED", "confidence_score": 1.0, "source_file": "docs/data-model.md", "source_location": null, "weight": 1.0}, {"source": "table_review_sections", "target": "table_review_responses", "relation": "shares_data_with", "confidence": "EXTRACTED", "confidence_score": 1.0, "source_file": "docs/data-model.md", "source_location": null, "weight": 1.0}, {"source": "table_courses", "target": "status_course_created", "relation": "references", "confidence": "EXTRACTED", "confidence_score": 1.0, "source_file": "docs/data-model.md", "source_location": null, "weight": 1.0}, {"source": "table_review_sections", "target": "review_section_course_metadata", "relation": "references", "confidence": "EXTRACTED", "confidence_score": 1.0, "source_file": "docs/data-model.md", "source_location": null, "weight": 1.0}, {"source": "table_review_sections", "target": "review_section_review_matrix", "relation": "references", "confidence": "EXTRACTED", "confidence_score": 1.0, "source_file": "docs/data-model.md", "source_location": null, "weight": 1.0}, {"source": "table_review_sections", "target": "review_section_syllabus_review", "relation": "references", "confidence": "EXTRACTED", "confidence_score": 1.0, "source_file": "docs/data-model.md", "source_location": null, "weight": 1.0}, {"source": "table_review_sections", "target": "review_section_gradebook_review", "relation": "references", "confidence": "EXTRACTED", "confidence_score": 1.0, "source_file": "docs/data-model.md", "source_location": null, "weight": 1.0}, {"source": "table_review_sections", "target": "review_section_general_notes", "relation": "references", "confidence": "EXTRACTED", "confidence_score": 1.0, "source_file": "docs/data-model.md", "source_location": null, "weight": 1.0}, {"source": "role_instructor", "target": "table_review_invites", "relation": "conceptually_related_to", "confidence": "INFERRED", "confidence_score": 0.85, "source_file": "docs/data-model.md", "source_location": null, "weight": 1.0}, {"source": "table_course_assignments", "target": "table_profiles", "relation": "shares_data_with", "confidence": "EXTRACTED", "confidence_score": 1.0, "source_file": "docs/data-model.md", "source_location": null, "weight": 1.0}, {"source": "table_course_status_events", "target": "table_profiles", "relation": "shares_data_with", "confidence": "EXTRACTED", "confidence_score": 1.0, "source_file": "docs/data-model.md", "source_location": null, "weight": 1.0}, {"source": "table_course_comments", "target": "table_profiles", "relation": "shares_data_with", "confidence": "EXTRACTED", "confidence_score": 1.0, "source_file": "docs/data-model.md", "source_location": null, "weight": 1.0}, {"source": "table_review_invites", "target": "table_profiles", "relation": "shares_data_with", "confidence": "EXTRACTED", "confidence_score": 1.0, "source_file": "docs/data-model.md", "source_location": null, "weight": 1.0}, {"source": "table_review_responses", "target": "table_profiles", "relation": "shares_data_with", "confidence": "EXTRACTED", "confidence_score": 1.0, "source_file": "docs/data-model.md", "source_location": null, "weight": 1.0}, {"source": "auth_users_supabase", "target": "supabase_auth", "relation": "conceptually_related_to", "confidence": "EXTRACTED", "confidence_score": 1.0, "source_file": "docs/data-model.md", "source_location": null, "weight": 1.0}], "hyperedges": []}