{"nodes":[{"id":"seed_dev_script","label":"Dev Seed Script","file_type":"code","source_file":"scripts/seed-dev.mjs","source_location":null,"source_url":null,"captured_at":null,"author":null,"contributor":null},{"id":"apply_migration_script","label":"Apply Migration Script","file_type":"code","source_file":"scripts/apply-migration.mjs","source_location":null,"source_url":null,"captured_at":null,"author":null,"contributor":null},{"id":"seed_dev_ensureauthuser","label":"ensureAuthUser","file_type":"code","source_file":"scripts/seed-dev.mjs","source_location":"85","source_url":null,"captured_at":null,"author":null,"contributor":null},{"id":"seed_dev_finduserbyemail","label":"findUserByEmail","file_type":"code","source_file":"scripts/seed-dev.mjs","source_location":"109","source_url":null,"captured_at":null,"author":null,"contributor":null},{"id":"seed_dev_upsertprofiles","label":"upsertProfiles","file_type":"code","source_file":"scripts/seed-dev.mjs","source_location":"138","source_url":null,"captured_at":null,"author":null,"contributor":null},{"id":"seed_dev_seedcourses","label":"seedCourses","file_type":"code","source_file":"scripts/seed-dev.mjs","source_location":"150","source_url":null,"captured_at":null,"author":null,"contributor":null},{"id":"seed_dev_upsertcourse","label":"upsertCourse","file_type":"code","source_file":"scripts/seed-dev.mjs","source_location":"206","source_url":null,"captured_at":null,"author":null,"contributor":null},{"id":"seed_dev_upsertassignments","label":"upsertAssignments","file_type":"code","source_file":"scripts/seed-dev.mjs","source_location":"261","source_url":null,"captured_at":null,"author":null,"contributor":null},{"id":"seed_dev_ensurestatusevent","label":"ensureStatusEvent","file_type":"code","source_file":"scripts/seed-dev.mjs","source_location":"278","source_url":null,"captured_at":null,"author":null,"contributor":null},{"id":"seed_dev_seedreviewresponses","label":"seedReviewResponses","file_type":"code","source_file":"scripts/seed-dev.mjs","source_location":"308","source_url":null,"captured_at":null,"author":null,"contributor":null},{"id":"seed_dev_loadenvfiles","label":"loadEnvFiles (seed-dev)","file_type":"code","source_file":"scripts/seed-dev.mjs","source_location":"342","source_url":null,"captured_at":null,"author":null,"contributor":null},{"id":"apply_migration_loadenvfiles","label":"loadEnvFiles (apply-migration)","file_type":"code","source_file":"scripts/apply-migration.mjs","source_location":"47","source_url":null,"captured_at":null,"author":null,"contributor":null},{"id":"apply_migration_parsedatabaseurl","label":"parseDatabaseUrl","file_type":"code","source_file":"scripts/apply-migration.mjs","source_location":"78","source_url":null,"captured_at":null,"author":null,"contributor":null},{"id":"apply_migration_parsesupabasedatabaseurl","label":"parseSupabaseDatabaseUrl","file_type":"code","source_file":"scripts/apply-migration.mjs","source_location":"89","source_url":null,"captured_at":null,"author":null,"contributor":null},{"id":"db_table_profiles","label":"DB Table: profiles","file_type":"code","source_file":"scripts/seed-dev.mjs","source_location":null,"source_url":null,"captured_at":null,"author":null,"contributor":null},{"id":"db_table_courses","label":"DB Table: courses","file_type":"code","source_file":"scripts/seed-dev.mjs","source_location":null,"source_url":null,"captured_at":null,"author":null,"contributor":null},{"id":"db_table_course_assignments","label":"DB Table: course_assignments","file_type":"code","source_file":"scripts/seed-dev.mjs","source_location":null,"source_url":null,"captured_at":null,"author":null,"contributor":null},{"id":"db_table_course_status_events","label":"DB Table: course_status_events","file_type":"code","source_file":"scripts/seed-dev.mjs","source_location":null,"source_url":null,"captured_at":null,"author":null,"contributor":null},{"id":"db_table_review_sections","label":"DB Table: review_sections","file_type":"code","source_file":"scripts/seed-dev.mjs","source_location":null,"source_url":null,"captured_at":null,"author":null,"contributor":null},{"id":"db_table_review_responses","label":"DB Table: review_responses","file_type":"code","source_file":"scripts/seed-dev.mjs","source_location":null,"source_url":null,"captured_at":null,"author":null,"contributor":null},{"id":"web_proxy","label":"Next.js Proxy Middleware","file_type":"code","source_file":"apps/web/proxy.ts","source_location":null,"source_url":null,"captured_at":null,"author":null,"contributor":null},{"id":"web_layout","label":"Root Layout (RootLayout)","file_type":"code","source_file":"apps/web/app/layout.tsx","source_location":null,"source_url":null,"captured_at":null,"author":null,"contributor":null},{"id":"web_page_home","label":"Home Page","file_type":"code","source_file":"apps/web/app/page.tsx","source_location":null,"source_url":null,"captured_at":null,"author":null,"contributor":null},{"id":"web_page_checkemail","label":"Check Email Auth Page","file_type":"code","source_file":"apps/web/app/auth/check-email/page.tsx","source_location":null,"source_url":null,"captured_at":null,"author":null,"contributor":null},{"id":"web_auth_callback_route","label":"Auth Callback Route Handler","file_type":"code","source_file":"apps/web/app/auth/callback/route.ts","source_location":null,"source_url":null,"captured_at":null,"author":null,"contributor":null},{"id":"lib_supabase_middleware","label":"Supabase Middleware (updateSession)","file_type":"code","source_file":"apps/web/lib/supabase/middleware.ts","source_location":null,"source_url":null,"captured_at":null,"author":null,"contributor":null},{"id":"lib_supabase_server","label":"Supabase Server Client (createClient)","file_type":"code","source_file":"apps/web/lib/supabase/server.ts","source_location":null,"source_url":null,"captured_at":null,"author":null,"contributor":null},{"id":"components_dev_role_switcher","label":"DevRoleSwitcher Component","file_type":"code","source_file":"apps/web/components/dev-role-switcher.tsx","source_location":null,"source_url":null,"captured_at":null,"author":null,"contributor":null},{"id":"lib_utils_cn","label":"cn Utility (classnames)","file_type":"code","source_file":"apps/web/lib/utils.ts","source_location":null,"source_url":null,"captured_at":null,"author":null,"contributor":null},{"id":"workflow_course_statuses","label":"COURSE_STATUSES Constant","file_type":"code","source_file":"packages/workflow/src/index.ts","source_location":null,"source_url":null,"captured_at":null,"author":null,"contributor":null},{"id":"workflow_roles","label":"ROLES Constant","file_type":"code","source_file":"packages/workflow/src/index.ts","source_location":null,"source_url":null,"captured_at":null,"author":null,"contributor":null},{"id":"workflow_getrolelabel","label":"getRoleLabel Function","file_type":"code","source_file":"packages/workflow/src/index.ts","source_location":null,"source_url":null,"captured_at":null,"author":null,"contributor":null},{"id":"ui_badge","label":"Badge UI Component","file_type":"code","source_file":"packages/ui/src/index.ts","source_location":null,"source_url":null,"captured_at":null,"author":null,"contributor":null},{"id":"ui_card","label":"Card UI Components","file_type":"code","source_file":"apps/web/components/ui/card.tsx","source_location":null,"source_url":null,"captured_at":null,"author":null,"contributor":null},{"id":"postcss_config","label":"PostCSS Config (Tailwind)","file_type":"code","source_file":"apps/web/postcss.config.mjs","source_location":null,"source_url":null,"captured_at":null,"author":null,"contributor":null},{"id":"dev_role_ta","label":"Dev Role: TA","file_type":"code","source_file":"scripts/seed-dev.mjs","source_location":null,"source_url":null,"captured_at":null,"author":null,"contributor":null},{"id":"dev_role_admin","label":"Dev Role: Admin","file_type":"code","source_file":"scripts/seed-dev.mjs","source_location":null,"source_url":null,"captured_at":null,"author":null,"contributor":null},{"id":"dev_role_communications","label":"Dev Role: Communications","file_type":"code","source_file":"scripts/seed-dev.mjs","source_location":null,"source_url":null,"captured_at":null,"author":null,"contributor":null},{"id":"dev_role_instructor","label":"Dev Role: Instructor","file_type":"code","source_file":"scripts/seed-dev.mjs","source_location":null,"source_url":null,"captured_at":null,"author":null,"contributor":null},{"id":"dev_role_super_admin","label":"Dev Role: Super Admin","file_type":"code","source_file":"scripts/seed-dev.mjs","source_location":null,"source_url":null,"captured_at":null,"author":null,"contributor":null}],"edges":[{"source":"seed_dev_ensureauthuser","target":"seed_dev_finduserbyemail","relation":"calls","confidence":"EXTRACTED","confidence_score":1.0,"source_file":"scripts/seed-dev.mjs","source_location":"86","weight":1.0},{"source":"seed_dev_script","target":"seed_dev_ensureauthuser","relation":"calls","confidence":"EXTRACTED","confidence_score":1.0,"source_file":"scripts/seed-dev.mjs","source_location":"62","weight":1.0},{"source":"seed_dev_script","target":"seed_dev_upsertprofiles","relation":"calls","confidence":"EXTRACTED","confidence_score":1.0,"source_file":"scripts/seed-dev.mjs","source_location":"71","weight":1.0},{"source":"seed_dev_script","target":"seed_dev_seedcourses","relation":"calls","confidence":"EXTRACTED","confidence_score":1.0,"source_file":"scripts/seed-dev.mjs","source_location":"72","weight":1.0},{"source":"seed_dev_seedcourses","target":"seed_dev_upsertcourse","relation":"calls","confidence":"EXTRACTED","confidence_score":1.0,"source_file":"scripts/seed-dev.mjs","source_location":"199","weight":1.0},{"source":"seed_dev_seedcourses","target":"seed_dev_upsertassignments","relation":"calls","confidence":"EXTRACTED","confidence_score":1.0,"source_file":"scripts/seed-dev.mjs","source_location":"200","weight":1.0},{"source":"seed_dev_seedcourses","target":"seed_dev_ensurestatusevent","relation":"calls","confidence":"EXTRACTED","confidence_score":1.0,"source_file":"scripts/seed-dev.mjs","source_location":"201","weight":1.0},{"source":"seed_dev_seedcourses","target":"seed_dev_seedreviewresponses","relation":"calls","confidence":"EXTRACTED","confidence_score":1.0,"source_file":"scripts/seed-dev.mjs","source_location":"202","weight":1.0},{"source":"seed_dev_upsertprofiles","target":"db_table_profiles","relation":"shares_data_with","confidence":"EXTRACTED","confidence_score":1.0,"source_file":"scripts/seed-dev.mjs","source_location":"139","weight":1.0},{"source":"seed_dev_upsertcourse","target":"db_table_courses","relation":"shares_data_with","confidence":"EXTRACTED","confidence_score":1.0,"source_file":"scripts/seed-dev.mjs","source_location":"208","weight":1.0},{"source":"seed_dev_upsertassignments","target":"db_table_course_assignments","relation":"shares_data_with","confidence":"EXTRACTED","confidence_score":1.0,"source_file":"scripts/seed-dev.mjs","source_location":"269","weight":1.0},{"source":"seed_dev_ensurestatusevent","target":"db_table_course_status_events","relation":"shares_data_with","confidence":"EXTRACTED","confidence_score":1.0,"source_file":"scripts/seed-dev.mjs","source_location":"280","weight":1.0},{"source":"seed_dev_seedreviewresponses","target":"db_table_review_sections","relation":"shares_data_with","confidence":"EXTRACTED","confidence_score":1.0,"source_file":"scripts/seed-dev.mjs","source_location":"309","weight":1.0},{"source":"seed_dev_seedreviewresponses","target":"db_table_review_responses","relation":"shares_data_with","confidence":"EXTRACTED","confidence_score":1.0,"source_file":"scripts/seed-dev.mjs","source_location":"333","weight":1.0},{"source":"seed_dev_script","target":"seed_dev_loadenvfiles","relation":"calls","confidence":"EXTRACTED","confidence_score":1.0,"source_file":"scripts/seed-dev.mjs","source_location":"35","weight":1.0},{"source":"apply_migration_script","target":"apply_migration_loadenvfiles","relation":"calls","confidence":"EXTRACTED","confidence_score":1.0,"source_file":"scripts/apply-migration.mjs","source_location":"8","weight":1.0},{"source":"apply_migration_script","target":"apply_migration_parsedatabaseurl","relation":"calls","confidence":"EXTRACTED","confidence_score":1.0,"source_file":"scripts/apply-migration.mjs","source_location":"29","weight":1.0},{"source":"apply_migration_parsedatabaseurl","target":"apply_migration_parsesupabasedatabaseurl","relation":"calls","confidence":"EXTRACTED","confidence_score":1.0,"source_file":"scripts/apply-migration.mjs","source_location":"85","weight":1.0},{"source":"web_proxy","target":"lib_supabase_middleware","relation":"calls","confidence":"EXTRACTED","confidence_score":1.0,"source_file":"apps/web/proxy.ts","source_location":"5","weight":1.0},{"source":"web_layout","target":"components_dev_role_switcher","relation":"references","confidence":"EXTRACTED","confidence_score":1.0,"source_file":"apps/web/app/layout.tsx","source_location":"4","weight":1.0},{"source":"web_layout","target":"lib_utils_cn","relation":"calls","confidence":"EXTRACTED","confidence_score":1.0,"source_file":"apps/web/app/layout.tsx","source_location":"5","weight":1.0},{"source":"web_page_home","target":"workflow_course_statuses","relation":"references","confidence":"EXTRACTED","confidence_score":1.0,"source_file":"apps/web/app/page.tsx","source_location":"1","weight":1.0},{"source":"web_page_home","target":"workflow_roles","relation":"references","confidence":"EXTRACTED","confidence_score":1.0,"source_file":"apps/web/app/page.tsx","source_location":"1","weight":1.0},{"source":"web_page_home","target":"workflow_getrolelabel","relation":"calls","confidence":"EXTRACTED","confidence_score":1.0,"source_file":"apps/web/app/page.tsx","source_location":"1","weight":1.0},{"source":"web_page_home","target":"ui_badge","relation":"references","confidence":"EXTRACTED","confidence_score":1.0,"source_file":"apps/web/app/page.tsx","source_location":"9","weight":1.0},{"source":"web_page_home","target":"ui_card","relation":"references","confidence":"EXTRACTED","confidence_score":1.0,"source_file":"apps/web/app/page.tsx","source_location":"3","weight":1.0},{"source":"web_auth_callback_route","target":"lib_supabase_server","relation":"calls","confidence":"EXTRACTED","confidence_score":1.0,"source_file":"apps/web/app/auth/callback/route.ts","source_location":"3","weight":1.0},{"source":"seed_dev_loadenvfiles","target":"apply_migration_loadenvfiles","relation":"semantically_similar_to","confidence":"INFERRED","confidence_score":0.92,"source_file":"scripts/seed-dev.mjs","source_location":null,"weight":0.9},{"source":"web_proxy","target":"web_auth_callback_route","relation":"conceptually_related_to","confidence":"INFERRED","confidence_score":0.75,"source_file":"apps/web/proxy.ts","source_location":null,"weight":0.75},{"source":"db_table_courses","target":"db_table_course_assignments","relation":"conceptually_related_to","confidence":"INFERRED","confidence_score":0.88,"source_file":"scripts/seed-dev.mjs","source_location":null,"weight":0.88},{"source":"db_table_courses","target":"db_table_course_status_events","relation":"conceptually_related_to","confidence":"INFERRED","confidence_score":0.88,"source_file":"scripts/seed-dev.mjs","source_location":null,"weight":0.88},{"source":"db_table_review_sections","target":"db_table_review_responses","relation":"conceptually_related_to","confidence":"INFERRED","confidence_score":0.9,"source_file":"scripts/seed-dev.mjs","source_location":null,"weight":0.9},{"source":"seed_dev_seedcourses","target":"dev_role_ta","relation":"references","confidence":"EXTRACTED","confidence_score":1.0,"source_file":"scripts/seed-dev.mjs","source_location":"152","weight":1.0},{"source":"seed_dev_seedcourses","target":"dev_role_admin","relation":"references","confidence":"EXTRACTED","confidence_score":1.0,"source_file":"scripts/seed-dev.mjs","source_location":"151","weight":1.0},{"source":"seed_dev_seedcourses","target":"dev_role_communications","relation":"references","confidence":"EXTRACTED","confidence_score":1.0,"source_file":"scripts/seed-dev.mjs","source_location":"153","weight":1.0},{"source":"seed_dev_seedcourses","target":"dev_role_instructor","relation":"references","confidence":"EXTRACTED","confidence_score":1.0,"source_file":"scripts/seed-dev.mjs","source_location":"154","weight":1.0},{"source":"seed_dev_seedcourses","target":"dev_role_super_admin","relation":"references","confidence":"EXTRACTED","confidence_score":1.0,"source_file":"scripts/seed-dev.mjs","source_location":"155","weight":1.0}],"hyperedges":[{"id":"seed_dev_full_pipeline","label":"Dev Seed Full Pipeline: Auth + Profiles + Courses + Assignments + Status Events + Review Responses","nodes":["seed_dev_ensureauthuser","seed_dev_upsertprofiles","seed_dev_seedcourses","seed_dev_upsertassignments","seed_dev_ensurestatusevent","seed_dev_seedreviewresponses"],"relation":"implement","confidence":"EXTRACTED","confidence_score":0.95,"source_file":"scripts/seed-dev.mjs"},{"id":"auth_flow_nodes","label":"Auth Flow: Proxy Session Update + Callback Code Exchange + Check Email UI","nodes":["web_proxy","web_auth_callback_route","web_page_checkemail"],"relation":"participate_in","confidence":"INFERRED","confidence_score":0.82,"source_file":"apps/web/app/auth/callback/route.ts"},{"id":"course_db_schema","label":"Course Data Schema: courses + assignments + status events","nodes":["db_table_courses","db_table_course_assignments","db_table_course_status_events"],"relation":"form","confidence":"INFERRED","confidence_score":0.9,"source_file":"scripts/seed-dev.mjs"}],"input_tokens":0,"output_tokens":0}